{"version":1,"resource":"file:///home/mouad/Documents/Epitech/Piscine/T-POO-700-STG_8/TimeManager/lib/time_manager/timetracking/infrastructure/repositories/working-time.repository.ex","entries":[{"id":"2Yvq.ex","timestamp":1728458257142},{"id":"gJbs.ex","timestamp":1728458289009},{"id":"ZqDO.ex","timestamp":1728458302880},{"id":"acEB.ex","timestamp":1728458346327},{"id":"0oQM.ex","timestamp":1728458372778},{"id":"uMhb.ex","timestamp":1728458406182},{"id":"pERM.ex","timestamp":1728458584815},{"id":"7VBy.ex","timestamp":1728458603955},{"id":"Pnx6.ex","timestamp":1728458686552},{"id":"lIUg.ex","timestamp":1728458796384},{"id":"4JL3.ex","timestamp":1728460030659},{"id":"1OXE.ex","timestamp":1728460060826},{"id":"JY1N.ex","timestamp":1728460071317},{"id":"pKMf.ex","timestamp":1728461553485},{"id":"4fSn.ex","timestamp":1728464178980},{"id":"FrYC.ex","timestamp":1728464192991},{"id":"vIBe.ex","timestamp":1728469010792},{"id":"GaIU.ex","timestamp":1728469187655},{"id":"s7lq.ex","timestamp":1728469369687},{"id":"lugC.ex","timestamp":1728469694249},{"id":"38Z9.ex","timestamp":1728470552312},{"id":"haZ9.ex","timestamp":1728470575628},{"id":"yXOH.ex","timestamp":1728470851945},{"id":"bM7E.ex","timestamp":1728471059310},{"id":"OqZF.ex","timestamp":1728471313565},{"id":"cVJB.ex","timestamp":1728471439821},{"id":"Td5t.ex","source":"undoRedo.source","timestamp":1728471443784},{"id":"szZf.ex","timestamp":1728471492131},{"id":"ThTN.ex","timestamp":1728471514654},{"id":"SgOT.ex","timestamp":1728471540887},{"id":"0qds.ex","timestamp":1728471558752},{"id":"IEV8.ex","timestamp":1728471596684},{"id":"PdMq.ex","timestamp":1728471701196},{"id":"Ycqn.ex","timestamp":1728471807257},{"id":"fO6i.ex","timestamp":1728471851233},{"id":"ry4F.ex","timestamp":1728471863132},{"id":"Elj8.ex","timestamp":1728471900366},{"id":"xGzP.ex","timestamp":1728471936125},{"id":"ICE7.ex","timestamp":1728472019199},{"id":"wENU.ex","timestamp":1728472037299},{"id":"pjb7.ex","timestamp":1728472074870},{"id":"PTDA.ex","timestamp":1728472292774},{"id":"71lK.ex","timestamp":1728473164005},{"id":"8PDA.ex","timestamp":1728473201653},{"id":"nOuT.ex","timestamp":1728476520271},{"id":"4wzj.ex","timestamp":1728477737828},{"id":"MkEj.ex","timestamp":1728478171173}]}