{"version":1,"resource":"file:///home/mouad/Documents/Universite/MasterI3D/Compile/Projet/cmat/include/sym_tab.h","entries":[{"id":"PWkk.h","timestamp":1701769448275},{"id":"q2nh.h","timestamp":1701769474567},{"id":"anci.h","source":"undoRedo.source","timestamp":1701769481619},{"id":"oWr9.h","timestamp":1701769486499},{"id":"l5iU.h","timestamp":1701769497007},{"id":"HZl9.h","timestamp":1701769515304},{"id":"wyTy.h","timestamp":1701769524264},{"id":"3TNn.h","timestamp":1701769597432},{"id":"d0Op.h","timestamp":1701769614612},{"id":"ZXIO.h","timestamp":1701769644201},{"id":"KfdI.h","timestamp":1701769665025},{"id":"GTpn.h","timestamp":1701771818651},{"id":"9cYJ.h","timestamp":1701771865135},{"id":"G91K.h","timestamp":1701771900224},{"id":"qsvC.h","timestamp":1701772044402},{"id":"KwnQ.h","timestamp":1701772055574},{"id":"pZXj.h","timestamp":1701774494616}]}